argson/__init__.py
argson/argson.py
argson-0.3.0.dist-info/LICENSE
argson-0.3.0.dist-info/WHEEL
argson-0.3.0.dist-info/METADATA
argson-0.3.0.dist-info/RECORD
