Metadata-Version: 2.1
Name: argson
Version: 0.3.0
Summary: Declare program arguments from JSON
Author: Gabriel Chamon Araujo
Author-email: gchamon@live.com
Requires-Python: >=3.6,<4.0
Classifier: Programming Language :: Python :: 3
Classifier: Programming Language :: Python :: 3.6
Classifier: Programming Language :: Python :: 3.7
Classifier: Programming Language :: Python :: 3.8
Requires-Dist: toml (>=0.10.0,<0.11.0)
